CHANGELOG.rst
LICENSE
MANIFEST.in
README.rst
hanzi-convert
pytest.ini
requirements.txt
runtests.py
setup.cfg
setup.py
hanziconv/__init__.py
hanziconv/charmap.py
hanziconv/hanziconv.py
hanziconv/specialnoun.py
hanziconv.egg-info/PKG-INFO
hanziconv.egg-info/SOURCES.txt
hanziconv.egg-info/dependency_links.txt
hanziconv.egg-info/top_level.txt